<mappings xmlns="http://dozer.sourceforge.net" xmlns:xsi="http://www.w3.org/2001/XMLSchema-instance"
    xsi:schemaLocation="http://dozer.sourceforge.net
          http://dozer.sourceforge.net/schema/beanmapping.xsd"> 
    <mapping date-format="yyyy-MM-dd" map-null="false" map-empty-string="false">
		<class-a>com.eduboss.domain.MoneyWashRecords</class-a>
		<class-b>com.eduboss.domainVo.MoneyWashRecordsVo</class-b>
		<field>
			<a>cause.id</a>
			<b>causeId</b>
		</field>
		<field>
			<a>cause.name</a>
			<b>causeName</b>
		</field>
		<field>
			<a>washOperator.userId</a>
			<b>washOperatorId</b>
		</field>
		<field>
			<a>washOperator.name</a>
			<b>washOperatorName</b>
		</field>
		<field>
			<a>modifyOperator.userId</a>
			<b>modifyOperatorId</b>
		</field>
		<field>
			<a>modifyOperator.name</a>
			<b>modifyOperatorName</b>
		</field>
		<field>
			<a>blCampusId.id</a>
			<b>blCampusId</b>
		</field>
		<field>
			<a>blCampusId.name</a>
			<b>blCampusName</b>
		</field>
		<field>
			<a>student.id</a>
			<b>studentId</b>
		</field>
		<field>
			<a>student.name</a>
			<b>studentName</b>
		</field>
		<field>
			<a>chargeType.name</a>
			<b>chargeTypeName</b>
		</field>
		<field>
			<a>chargeType.value</a>
			<b>chargeTypeValue</b>
		</field>
		<field>
			<a>chargeType.name</a>
			<b>chargeTypeName</b>
		</field>
		<field>
			<a>chargeType.value</a>
			<b>chargeTypeValue</b>
		</field>
		<field>
			<a>productType.name</a>
			<b>productTypeName</b>
		</field>
		<field>
			<a>productType.value</a>
			<b>productTypeValue</b>
		</field>
		<field>
			<a>originalOperateUser.userId</a>
			<b>originalOperateUserId</b>
		</field>
		<field>
			<a>originalOperateUser.name</a>
			<b>originalOperateUserName</b>
		</field>
	</mapping>
</mappings>